pytracetoix/__init__.py
pytracetoix/pytracetoix.py
PyTraceToIX-1.2.1.dist-info/LICENSE
PyTraceToIX-1.2.1.dist-info/METADATA
PyTraceToIX-1.2.1.dist-info/WHEEL
PyTraceToIX-1.2.1.dist-info/top_level.txt
PyTraceToIX-1.2.1.dist-info/RECORD
