Metadata-Version: 2.1
Name: PyTraceToIX
Version: 1.2.1
Summary: An expression tracer for debugging lambdas, list comprehensions, method chaining, and expressions
Author-email: Alexandre Bento Freire <devtoix@a-bentofreire.com>
Project-URL: Homepage, https://www.devtoix.com/en/projects/pytracetoix
Project-URL: Documentation, https://www.devtoix.com/docs/pytracetoix/en/
Project-URL: Repository, https://github.com/a-bentofreire/pytracetoix
Project-URL: Issues, https://github.com/a-bentofreire/pytracetoix/issues
Project-URL: Changelog, https://github.com/a-bentofreire/pytracetoix/blob/HEAD/CHANGELOG.md
Project-URL: Twitter, https://x.com/devtoix
Keywords: debugging,tracer,debug,log,logger,expression,lambda,list comprehensions
Classifier: Programming Language :: Python :: 3
Classifier: License :: OSI Approved :: MIT License
Classifier: Operating System :: OS Independent
Requires-Python: >=3.9
License-File: LICENSE
